milvus_kernel/__init__.py
milvus_kernel/__main__.py
milvus_kernel/install.py
milvus_kernel/kernel.py
milvus_kernel-0.2.0.dist-info/LICENSE
milvus_kernel-0.2.0.dist-info/METADATA
milvus_kernel-0.2.0.dist-info/WHEEL
milvus_kernel-0.2.0.dist-info/top_level.txt
milvus_kernel-0.2.0.dist-info/RECORD
