Metadata-Version: 2.1
Name: milvus-kernel
Version: 0.2.0
Summary: A milvus kernel for Jupyter.
Home-page: https://github.com/Hourout/milvus_kernel
Author: JinQing Lee
Author-email: hourout@163.com
License: Apache License Version 2.0
Keywords: jupyter_kernel,milvus_kernel,milvus
Platform: UNKNOWN
Classifier: Framework :: IPython
Classifier: License :: OSI Approved :: Apache Software License
Classifier: Programming Language :: Python :: 3.6
Classifier: Programming Language :: Python :: 3.7
Classifier: Programming Language :: Python :: 3.8
Classifier: Intended Audience :: Developers
Classifier: Intended Audience :: Education
Classifier: Intended Audience :: Science/Research
Classifier: Topic :: Scientific/Engineering
Classifier: Topic :: System :: Shells
Requires-Dist: pymilvus
Requires-Dist: pandas
Requires-Dist: jupyter
